TACTICS/__init__.py
TACTICS/data/__init__.py
TACTICS/data/thrombin/__init__.py
TACTICS/data/thrombin/acids.smi
TACTICS/data/thrombin/amino_acids_no_fmoc.smi
TACTICS/data/thrombin/coupled_aa_sub.smi
TACTICS/data/thrombin/product_scores.csv
TACTICS/library_analysis/__init__.py
TACTICS/library_analysis/library_analysis.py
TACTICS/library_analysis/library_analysis_utils.py
TACTICS/library_analysis/visualization.py
TACTICS/library_enumeration/__init__.py
TACTICS/library_enumeration/conformer_gen.py
TACTICS/library_enumeration/enumeration_utils.py
TACTICS/library_enumeration/file_writer.py
TACTICS/library_enumeration/generate_products.py
TACTICS/library_enumeration/multiprocessing_utils.py
TACTICS/library_enumeration/synthesis_pipeline.py
TACTICS/library_enumeration/smarts_toolkit/__init__.py
TACTICS/library_enumeration/smarts_toolkit/_validator.py
TACTICS/library_enumeration/smarts_toolkit/config.py
TACTICS/library_enumeration/smarts_toolkit/constants.py
TACTICS/thompson_sampling/__init__.py
TACTICS/thompson_sampling/baseline.py
TACTICS/thompson_sampling/config.py
TACTICS/thompson_sampling/factories.py
TACTICS/thompson_sampling/presets.py
TACTICS/thompson_sampling/core/__init__.py
TACTICS/thompson_sampling/core/evaluator_config.py
TACTICS/thompson_sampling/core/evaluators.py
TACTICS/thompson_sampling/core/parallel_evaluator.py
TACTICS/thompson_sampling/core/reagent.py
TACTICS/thompson_sampling/core/sampler.py
TACTICS/thompson_sampling/legacy/baseline.py
TACTICS/thompson_sampling/legacy/config.py
TACTICS/thompson_sampling/legacy/disallow_tracker.py
TACTICS/thompson_sampling/legacy/enhanced_thompson_sampling.py
TACTICS/thompson_sampling/legacy/evaluators.py
TACTICS/thompson_sampling/legacy/reagent.py
TACTICS/thompson_sampling/legacy/rws_main.py
TACTICS/thompson_sampling/legacy/rws_reagent.py
TACTICS/thompson_sampling/legacy/rws_run.py
TACTICS/thompson_sampling/legacy/rws_sampling.py
TACTICS/thompson_sampling/legacy/rws_utils.py
chem_tactics-1.0.1.dist-info/licenses/LICENSE
chem_tactics-1.0.1.dist-info/METADATA
chem_tactics-1.0.1.dist-info/WHEEL
chem_tactics-1.0.1.dist-info/top_level.txt
chem_tactics-1.0.1.dist-info/RECORD
