Metadata-Version: 2.4
Name: chem-tactics
Version: 1.0.1
Summary: Thompson Sampling-Assisted Chemical Targeting and Iterative Compound Selection for Drug Discovery
Author-email: Aakankschit Nandkeolyar <anandkeo@uci.edu>, "Remco L. van den Broek" <r.l.van.den.broek@lacdr.leidenuniv.nl>, Willem Jespers <w.jespers@rug.nl>
License: MIT
Project-URL: Homepage, https://github.com/aakankschit/TACTICS
Project-URL: Documentation, https://aakankschit.github.io/TACTICS/
Project-URL: Repository, https://github.com/aakankschit/TACTICS
Project-URL: Issues, https://github.com/aakankschit/TACTICS/issues
Keywords: thompson-sampling,drug-discovery,combinatorial-chemistry,optimization,cheminformatics
Classifier: Development Status :: 5 - Production/Stable
Classifier: Intended Audience :: Science/Research
Classifier: Topic :: Scientific/Engineering :: Chemistry
Classifier: Topic :: Scientific/Engineering :: Bio-Informatics
Classifier: License :: OSI Approved :: MIT License
Classifier: Programming Language :: Python :: 3
Classifier: Programming Language :: Python :: 3.11
Classifier: Programming Language :: Python :: 3.12
Requires-Python: >=3.11
License-File: LICENSE
Requires-Dist: pydantic>=2.0
Requires-Dist: rdkit
Requires-Dist: numpy
Requires-Dist: scipy
Requires-Dist: pandas
Requires-Dist: polars
Requires-Dist: tqdm
Requires-Dist: sqlitedict
Requires-Dist: seaborn
Requires-Dist: matplotlib
Requires-Dist: altair
Requires-Dist: joblib
Requires-Dist: dill
Requires-Dist: useful_rdkit_utils
Provides-Extra: test
Requires-Dist: pytest; extra == "test"
Requires-Dist: pytest-cov; extra == "test"
Requires-Dist: ipython; extra == "test"
Provides-Extra: notebook
Requires-Dist: ipython; extra == "notebook"
Requires-Dist: ipykernel; extra == "notebook"
Provides-Extra: docs
Requires-Dist: sphinx>=7.0; extra == "docs"
Requires-Dist: pydata-sphinx-theme>=0.15; extra == "docs"
Requires-Dist: sphinx-design; extra == "docs"
Requires-Dist: sphinx-copybutton; extra == "docs"
Requires-Dist: sphinx-togglebutton; extra == "docs"
Requires-Dist: myst-nb>=1.0; extra == "docs"
Provides-Extra: openeye
Requires-Dist: openeye-toolkits; extra == "openeye"
Provides-Extra: tutorials
Requires-Dist: marimo>=0.18.0; extra == "tutorials"
Dynamic: license-file
